Metadata-Version: 1.2
Name: rewrapped
Version: 0.5.0
Summary: Class wrappers for regular expressions with proper fields for match groups.
Home-page: https://github.com/hansi-b/rewrapped
Author: Hans Bering
Author-email: hansi.b.github@moc.liamg
License: MIT
Platform: UNKNOWN
Classifier: Development Status :: 3 - Alpha
Classifier: Intended Audience :: Developers
Classifier: License :: OSI Approved :: MIT License
Classifier: Programming Language :: Python :: 3
Classifier: Topic :: Text Processing :: General
Classifier: Topic :: Utilities
Requires-Python: >=3
